batcat/Athena.py
batcat/Configure.py
batcat/Docker.py
batcat/FileSys.py
batcat/Lambda.py
batcat/Logging.py
batcat/Redshift.py
batcat/SageMaker.py
batcat/Stepfunctions.py
batcat/Storage.py
batcat/__init__.py
batcat/__version__.py
batcat/core.py
batcat-0.2.50.dist-info/LICENSE
batcat-0.2.50.dist-info/METADATA
batcat-0.2.50.dist-info/WHEEL
batcat-0.2.50.dist-info/top_level.txt
batcat-0.2.50.dist-info/RECORD
