Metadata-Version: 2.1
Name: batcat
Version: 0.2.50
Summary: BatCat, A Cat Looks Like A Bat.
Home-page: https://github.com/Ewen2015/BatCat
Author: Ewen Wang
Author-email: wolfgangwong2012@gmail.com
License: Apache License 2.0
Classifier: License :: OSI Approved :: Apache Software License
Classifier: Programming Language :: Python :: 3.9
License-File: LICENSE
Requires-Dist: pandas
Requires-Dist: boto3 ==1.34.26
Requires-Dist: protobuf ==3.19.5
Requires-Dist: sagemaker ==2.204.0
Requires-Dist: stepfunctions ==2.3.0
Requires-Dist: sagemaker-experiments ==0.1.35
Requires-Dist: pyathena ==2.3.0
Requires-Dist: redshift-connector ==2.0.888
Requires-Dist: sqlalchemy ==1.3.23
Requires-Dist: psycopg2-binary ==2.9.1
Requires-Dist: joblib ==1.2.0
Requires-Dist: requests
